grappelli_filters/__init__.py
grappelli_filters/admin.py
grappelli_filters/filters.py
grappelli_filters/models.py
grappelli_filters/tests.py
grappelli_filters/views.py
grappelli_filters/static/grappelli_filters/filter.css
grappelli_filters/static/grappelli_filters/filter.js
grappelli_filters/templates/grappelli_filters/related_autocomplete.html
grappelli_filters/templates/grappelli_filters/search.html
django_grappelli_filters2-1.0.2.dist-info/METADATA
django_grappelli_filters2-1.0.2.dist-info/WHEEL
django_grappelli_filters2-1.0.2.dist-info/top_level.txt
django_grappelli_filters2-1.0.2.dist-info/RECORD
